{
  "updated_at": "2026-04-12T00:26:50.898680-04:00",
  "games": [
    {
      "gamePk": 824859,
      "away_team": "San Francisco Giants",
      "home_team": "Baltimore Orioles",
      "venue": "Oriole Park at Camden Yards",
      "start": "2026-04-12T17:35:00Z",
      "status": "Preview",
      "away_pitcher": {
        "id": 605288,
        "name": "Adrian Houser",
        "hand": "R",
        "era": "3.97"
      },
      "home_pitcher": {
        "id": 700249,
        "name": "Cade Povich",
        "hand": "L",
        "era": "3.18"
      }
    },
    {
      "gamePk": 823479,
      "away_team": "Arizona Diamondbacks",
      "home_team": "Philadelphia Phillies",
      "venue": "Citizens Bank Park",
      "start": "2026-04-12T17:35:00Z",
      "status": "Preview",
      "away_pitcher": {
        "id": 668678,
        "name": "Zac Gallen",
        "hand": "R",
        "era": "3.00"
      },
      "home_pitcher": {
        "id": 691725,
        "name": "Andrew Painter",
        "hand": "R",
        "era": "4.82"
      }
    },
    {
      "gamePk": 822828,
      "away_team": "Minnesota Twins",
      "home_team": "Toronto Blue Jays",
      "venue": "Rogers Centre",
      "start": "2026-04-12T17:37:00Z",
      "status": "Preview",
      "away_pitcher": {
        "id": 671737,
        "name": "Taj Bradley",
        "hand": "R",
        "era": "1.08"
      },
      "home_pitcher": {
        "id": 453286,
        "name": "Max Scherzer",
        "hand": "R",
        "era": "3.38"
      }
    },
    {
      "gamePk": 824533,
      "away_team": "Los Angeles Angels",
      "home_team": "Cincinnati Reds",
      "venue": "Great American Ball Park",
      "start": "2026-04-12T17:40:00Z",
      "status": "Preview",
      "away_pitcher": {
        "id": 667755,
        "name": "Jos\u00e9 Soriano",
        "hand": "R",
        "era": "0.45"
      },
      "home_pitcher": {
        "id": 671096,
        "name": "Andrew Abbott",
        "hand": "L",
        "era": "3.18"
      }
    },
    {
      "gamePk": 823642,
      "away_team": "Athletics",
      "home_team": "New York Mets",
      "venue": "Citi Field",
      "start": "2026-04-12T17:40:00Z",
      "status": "Preview",
      "away_pitcher": {
        "id": 650644,
        "name": "Aaron Civale",
        "hand": "R",
        "era": "2.70"
      },
      "home_pitcher": {
        "id": 642547,
        "name": "Freddy Peralta",
        "hand": "R",
        "era": "4.80"
      }
    },
    {
      "gamePk": 824293,
      "away_team": "Miami Marlins",
      "home_team": "Detroit Tigers",
      "venue": "Comerica Park",
      "start": "2026-04-12T17:40:00Z",
      "status": "Preview",
      "away_pitcher": {
        "id": 645261,
        "name": "Sandy Alcantara",
        "hand": "R",
        "era": "0.74"
      },
      "home_pitcher": {
        "id": 669373,
        "name": "Tarik Skubal",
        "hand": "L",
        "era": "2.55"
      }
    },
    {
      "gamePk": 822998,
      "away_team": "New York Yankees",
      "home_team": "Tampa Bay Rays",
      "venue": "Tropicana Field",
      "start": "2026-04-12T17:40:00Z",
      "status": "Preview",
      "away_pitcher": {
        "id": 693645,
        "name": "Cam Schlittler",
        "hand": "R",
        "era": "1.62"
      },
      "home_pitcher": {
        "id": 656876,
        "name": "Drew Rasmussen",
        "hand": "R",
        "era": "1.80"
      }
    },
    {
      "gamePk": 824126,
      "away_team": "Chicago White Sox",
      "home_team": "Kansas City Royals",
      "venue": "Kauffman Stadium",
      "start": "2026-04-12T18:10:00Z",
      "status": "Preview",
      "away_pitcher": {
        "id": 691799,
        "name": "Grant Taylor",
        "hand": "R",
        "era": "1.42"
      },
      "home_pitcher": {
        "id": 702070,
        "name": "Noah Cameron",
        "hand": "L",
        "era": "1.69"
      }
    },
    {
      "gamePk": 823804,
      "away_team": "Washington Nationals",
      "home_team": "Milwaukee Brewers",
      "venue": "American Family Field",
      "start": "2026-04-12T18:10:00Z",
      "status": "Preview",
      "away_pitcher": {
        "id": 641793,
        "name": "Zack Littell",
        "hand": "R",
        "era": "3.60"
      },
      "home_pitcher": {
        "id": 605540,
        "name": "Brandon Woodruff",
        "hand": "R",
        "era": "5.91"
      }
    },
    {
      "gamePk": 823075,
      "away_team": "Boston Red Sox",
      "home_team": "St. Louis Cardinals",
      "venue": "Busch Stadium",
      "start": "2026-04-12T18:15:00Z",
      "status": "Preview",
      "away_pitcher": {
        "id": 678394,
        "name": "Brayan Bello",
        "hand": "R",
        "era": "9.00"
      },
      "home_pitcher": {
        "id": 669467,
        "name": "Andre Pallante",
        "hand": "R",
        "era": "1.80"
      }
    },
    {
      "gamePk": 824696,
      "away_team": "Pittsburgh Pirates",
      "home_team": "Chicago Cubs",
      "venue": "Wrigley Field",
      "start": "2026-04-12T18:20:00Z",
      "status": "Preview",
      "away_pitcher": {
        "id": 696149,
        "name": "Bubba Chandler",
        "hand": "R",
        "era": "3.12"
      },
      "home_pitcher": {
        "id": 592791,
        "name": "Jameson Taillon",
        "hand": "R",
        "era": "2.53"
      }
    },
    {
      "gamePk": 823317,
      "away_team": "Colorado Rockies",
      "home_team": "San Diego Padres",
      "venue": "Petco Park",
      "start": "2026-04-12T20:10:00Z",
      "status": "Preview",
      "away_pitcher": {
        "id": 607536,
        "name": "Kyle Freeland",
        "hand": "L",
        "era": "2.30"
      },
      "home_pitcher": {
        "id": 601713,
        "name": "Nick Pivetta",
        "hand": "R",
        "era": "5.54"
      }
    },
    {
      "gamePk": 823154,
      "away_team": "Houston Astros",
      "home_team": "Seattle Mariners",
      "venue": "T-Mobile Park",
      "start": "2026-04-12T20:10:00Z",
      "status": "Preview",
      "away_pitcher": {},
      "home_pitcher": {
        "id": 669302,
        "name": "Logan Gilbert",
        "hand": "R",
        "era": "5.40"
      }
    },
    {
      "gamePk": 823966,
      "away_team": "Texas Rangers",
      "home_team": "Los Angeles Dodgers",
      "venue": "UNIQLO Field at Dodger Stadium",
      "start": "2026-04-12T20:10:00Z",
      "status": "Preview",
      "away_pitcher": {
        "id": 594798,
        "name": "Jacob deGrom",
        "hand": "R",
        "era": "3.72"
      },
      "home_pitcher": {
        "id": 808963,
        "name": "Roki Sasaki",
        "hand": "R",
        "era": "7.00"
      }
    },
    {
      "gamePk": 824938,
      "away_team": "Cleveland Guardians",
      "home_team": "Atlanta Braves",
      "venue": "Truist Park",
      "start": "2026-04-12T23:20:00Z",
      "status": "Preview",
      "away_pitcher": {
        "id": 676440,
        "name": "Tanner Bibee",
        "hand": "R",
        "era": "3.29"
      },
      "home_pitcher": {
        "id": 519242,
        "name": "Chris Sale",
        "hand": "L",
        "era": "3.94"
      }
    }
  ],
  "errors": []
}