{
  "updated_at": "2026-04-11T15:47:23.244651-04:00",
  "games": [
    {
      "gamePk": 824697,
      "game": "Pittsburgh Pirates @ Chicago Cubs",
      "score": "3-0",
      "inning": "5th",
      "hot_hitters": [
        "Oneil Cruz",
        "Nick Yorke",
        "Mois\u00e9s Ballesteros"
      ],
      "top_pitchers": [
        "Braxton Ashcraft"
      ]
    },
    {
      "gamePk": 822830,
      "game": "Minnesota Twins @ Toronto Blue Jays",
      "score": "1-2",
      "inning": "3rd",
      "hot_hitters": [
        "Brooks Lee",
        "Daulton Varsho"
      ],
      "top_pitchers": []
    },
    {
      "gamePk": 823644,
      "game": "Athletics @ New York Mets",
      "score": "0-0",
      "inning": "1st",
      "hot_hitters": [],
      "top_pitchers": []
    }
  ],
  "errors": []
}