{
  "updated_at": "2026-04-26T07:58:34.034142-04:00",
  "date": "2026-04-25",
  "dashboard_recap": {
    "headline": "MLB Daily Recap - April 25, 2026",
    "article": "**\"MVPs Shine as Red Sox Rout Orioles 17-1\"**\n\nIn a dominant performance, the Boston Red Sox cruised past the Baltimore Orioles 17-1 behind Willson Contreras' 5-RBI outing, including a home run. Contreras finished with 2 hits and 1 home run in 4 at-bats. On the mound, Garrett Crochet threw 6 scoreless innings, striking out 7 and walking 2. His 6.0 IP, 7 K, 0 ER, 2 BB, 3 H line led the Red Sox to a convincing win.\n\nMeanwhile, the Seattle Mariners edged the St. Louis Cardinals 11-9, thanks in part to Nathan Church's 2-home run, 4-RBI performance. Church's 2 hits in 4 at-bats also led the Mariners' offense. In the Cleveland Guardians' 3-5 loss to the Toronto Blue Jays, Kazuma Okamoto notched 2 hits and 1 home run in 3 at-bats.\n\n**Other Notable Performances:**\n\n* Ty France went 2-for-4 with 2 home runs and 2 RBI to help the San Diego Padres top the Arizona Diamondbacks 6-4.\n* Josh Jung's 1-home run, 2-RBI outing led the Texas Rangers to a 4-3 win over the Athletics.\n* Cole Ragans threw 6 scoreless innings, striking out 11 in the Kansas City Royals' 12-1 victory over the Los Angeles Angels.\n* Austin Wells finished 2-for-3 with 1 home run and 2 RBI to help the New York Yankees defeat the Houston Astros 8-3.\n* Nick Gonzales went 3-for-5 with 1 RBI to lead the Pittsburgh Pirates past the Milwaukee Brewers 6-3.\n* Sal Stewart's 3 hits, including a home run, and 5 RBI powered the Cincinnati Reds to a 9-2 win over the Detroit Tigers.",
    "all_games": [
      {
        "game": "Boston Red Sox @ Baltimore Orioles",
        "final_score": "17-1",
        "top_pitching_line": "Garrett Crochet: 6.0 IP, 7 K, 0 ER, 2 BB, 3 H",
        "top_batting_line": "Willson Contreras: 2 H, 1 HR, 5 RBI, 4 AB",
        "summary": "The Boston Red Sox dominated the Baltimore Orioles 17-1 behind Garrett Crochet's 6 shutout innings and Willson Contreras' 5-RBI performance.",
        "impact_player": "Willson Contreras"
      },
      {
        "game": "Seattle Mariners @ St. Louis Cardinals",
        "final_score": "11-9",
        "top_pitching_line": "Jose A. Ferrer: 2.0 IP, 1 K, 0 ER, 1 BB, 2 H",
        "top_batting_line": "Nathan Church: 2 H, 2 HR, 4 RBI, 4 AB",
        "summary": "The Seattle Mariners outlasted the St. Louis Cardinals 11-9 behind Nathan Church's 2 HR and 4 RBI performance.",
        "impact_player": "Nathan Church"
      },
      {
        "game": "Cleveland Guardians @ Toronto Blue Jays",
        "final_score": "3-5",
        "top_pitching_line": "Connor Brogdon: 1.0 IP, 2 K, 0 ER, 0 BB, 0 H",
        "top_batting_line": "Kazuma Okamoto: 2 H, 1 HR, 2 RBI, 3 AB",
        "summary": "The Toronto Blue Jays edged the Cleveland Guardians 5-3, led by Kazuma Okamoto's 2 hits, 1 home run, and 2 RBIs.",
        "impact_player": "Kazuma Okamoto"
      },
      {
        "game": "Miami Marlins @ San Francisco Giants",
        "final_score": "2-6",
        "top_pitching_line": "Robbie Ray: 5.0 IP, 4 K, 1 ER, 3 BB, 4 H",
        "top_batting_line": "Casey Schmitt: 2 H, 1 HR, 2 RBI, 3 AB",
        "summary": "The San Francisco Giants defeated the Miami Marlins 6-2 behind Casey Schmitt's 2 hits, including a home run, and Robbie Ray's 5 strong innings.",
        "impact_player": "Casey Schmitt"
      },
      {
        "game": "Minnesota Twins @ Tampa Bay Rays",
        "final_score": "1-6",
        "top_pitching_line": "Shane McClanahan: 5.0 IP, 7 K, 0 ER, 2 BB, 3 H",
        "top_batting_line": "Jake Fraley: 1 H, 1 HR, 2 RBI, 2 AB",
        "summary": "Tampa Bay Rays dominated Minnesota Twins 6-1 behind Shane McClanahan's 5 shutout innings and Jake Fraley's 2 RBI, including a solo home run.",
        "impact_player": "Jake Fraley"
      },
      {
        "game": "Washington Nationals @ Chicago White Sox",
        "final_score": "6-3",
        "top_pitching_line": "Jake Irvin: 5.2 IP, 9 K, 0 ER, 0 BB, 4 H",
        "top_batting_line": "Nasim Nu\u00f1ez: 2 H, 0 HR, 4 RBI, 4 AB",
        "summary": "The Washington Nationals edged the Chicago White Sox 6-3 behind Jake Irvin's 5.2 scoreless innings and Nasim Nu\u00f1ez's 4 RBIs.",
        "impact_player": "Nasim Nu\u00f1ez"
      },
      {
        "game": "San Diego Padres @ Arizona Diamondbacks",
        "final_score": "6-4",
        "top_pitching_line": "Zac Gallen: 3.0 IP, 3 K, 0 ER, 0 BB, 1 H",
        "top_batting_line": "Ty France: 2 H, 2 HR, 2 RBI, 4 AB",
        "summary": "The San Diego Padres edged the Arizona Diamondbacks 6-4 behind Ty France's 2-home run, 2-RBI performance.",
        "impact_player": "Ty France"
      },
      {
        "game": "Athletics @ Texas Rangers",
        "final_score": "3-4",
        "top_pitching_line": "MacKenzie Gore: 5.0 IP, 7 K, 3 ER, 3 BB, 6 H",
        "top_batting_line": "Josh Jung: 1 H, 1 HR, 2 RBI, 4 AB",
        "summary": "The Texas Rangers edged the Athletics 4-3 behind Josh Jung's 2-RBI, 4th home run of the season, a fly ball to right center.",
        "impact_player": "Josh Jung"
      },
      {
        "game": "Los Angeles Angels @ Kansas City Royals",
        "final_score": "1-12",
        "top_pitching_line": "Cole Ragans: 6.0 IP, 11 K, 1 ER, 0 BB, 5 H",
        "top_batting_line": "Salvador Perez: 3 H, 1 HR, 2 RBI, 5 AB",
        "summary": "The Kansas City Royals dominated the Los Angeles Angels 12-1 behind Cole Ragans' 6 shutout innings and Salvador Perez's 3-hit, 2-RBI performance.",
        "impact_player": "Salvador Perez"
      },
      {
        "game": "New York Yankees @ Houston Astros",
        "final_score": "8-3",
        "top_pitching_line": "Mike Burrows: 5.0 IP, 8 K, 2 ER, 3 BB, 5 H",
        "top_batting_line": "Austin Wells: 2 H, 1 HR, 2 RBI, 3 AB",
        "summary": "The New York Yankees defeated the Houston Astros 8-3 behind Austin Wells' 2 hits, 1 home run, and 2 RBIs, and Mike Burrows' 5 strong innings.",
        "impact_player": "Austin Wells"
      },
      {
        "game": "Pittsburgh Pirates @ Milwaukee Brewers",
        "final_score": "6-3",
        "top_pitching_line": "Jacob Misiorowski: 6.0 IP, 9 K, 3 ER, 1 BB, 6 H",
        "top_batting_line": "Nick Gonzales: 3 H, 0 HR, 1 RBI, 5 AB",
        "summary": "The Pittsburgh Pirates edged the Milwaukee Brewers 6-3 behind Jacob Misiorowski's 6 strong innings and Nick Gonzales' 3-hit performance with a key 2-run single.",
        "impact_player": "Nick Gonzales"
      },
      {
        "game": "Detroit Tigers @ Cincinnati Reds",
        "final_score": "2-9",
        "top_pitching_line": "Drew Anderson: 2.2 IP, 5 K, 1 ER, 1 BB, 1 H",
        "top_batting_line": "Sal Stewart: 3 H, 1 HR, 5 RBI, 4 AB",
        "summary": "The Cincinnati Reds dominated the Detroit Tigers 9-2, led by Sal Stewart's 3 hits, 1 home run, and 5 RBIs, and Drew Anderson's 2.2 scoreless innings.",
        "impact_player": "Sal Stewart"
      },
      {
        "game": "Chicago Cubs @ Los Angeles Dodgers",
        "final_score": "4-12",
        "top_pitching_line": "Will Klein: 1.1 IP, 2 K, 0 ER, 0 BB, 1 H",
        "top_batting_line": "Seiya Suzuki: 3 H, 1 HR, 1 RBI, 4 AB",
        "summary": "The Los Angeles Dodgers dominated the Chicago Cubs 12-4, led by Seiya Suzuki's 3 hits and home run, and a strong relief outing from Will Klein.",
        "impact_player": "Seiya Suzuki"
      },
      {
        "game": "Philadelphia Phillies @ Atlanta Braves",
        "final_score": "8-5",
        "top_pitching_line": "Zack Wheeler: 5.0 IP, 6 K, 2 ER, 3 BB, 3 H",
        "top_batting_line": "Bryce Harper: 2 H, 0 HR, 4 RBI, 3 AB",
        "summary": "The Philadelphia Phillies defeated the Atlanta Braves 8-5 behind Zack Wheeler's 5 strong innings, striking out 6, and Bryce Harper's 4 RBI performance.",
        "impact_player": "Bryce Harper"
      },
      {
        "game": "Colorado Rockies @ New York Mets",
        "final_score": "0-0",
        "top_pitching_line": "No standout pitching line available.",
        "top_batting_line": "No standout batting line available.",
        "summary": "The New York Mets edged the Colorado Rockies 0-0, with a shutout performance on both sides.",
        "impact_player": "N/A"
      }
    ],
    "season_leaders": {
      "avg_ops": [
        "Yordan Alvarez (Houston Astros) - AVG .353",
        "Xavier Edwards (Miami Marlins) - AVG .353",
        "Ben Rice (New York Yankees) - AVG .337",
        "Andy Pages (Los Angeles Dodgers) - AVG .337",
        "Yandy D\u00edaz (Tampa Bay Rays) - AVG .337",
        "Yordan Alvarez (Houston Astros) - OPS 1.219",
        "Ben Rice (New York Yankees) - OPS 1.216",
        "Max Muncy (Los Angeles Dodgers) - OPS 1.027",
        "Sal Stewart (Cincinnati Reds) - OPS 1.024",
        "James Wood (Washington Nationals) - OPS .975"
      ],
      "power": [
        "Yordan Alvarez (Houston Astros) - HR 11",
        "Munetaka Murakami (Chicago White Sox) - HR 11",
        "James Wood (Washington Nationals) - HR 10",
        "Elly De La Cruz (Cincinnati Reds) - HR 9",
        "Aaron Judge (New York Yankees) - HR 9",
        "Max Muncy (Los Angeles Dodgers) - HR 9",
        "Ben Rice (New York Yankees) - HR 9",
        "Sal Stewart (Cincinnati Reds) - HR 9",
        "Sal Stewart (Cincinnati Reds) - RBI 29",
        "Yordan Alvarez (Houston Astros) - RBI 26",
        "Drake Baldwin (Atlanta Braves) - RBI 24",
        "Oneil Cruz (Pittsburgh Pirates) - RBI 24",
        "Liam Hicks (Miami Marlins) - RBI 24",
        "Andy Pages (Los Angeles Dodgers) - RBI 24"
      ],
      "pitching": [
        "Jacob Misiorowski (Milwaukee Brewers) - K 51",
        "Dylan Cease (Toronto Blue Jays) - K 44",
        "Gavin Williams (Cleveland Guardians) - K 44",
        "Jos\u00e9 Soriano (Los Angeles Angels) - K 43",
        "Cristopher S\u00e1nchez (Philadelphia Phillies) - K 43",
        "Aaron Ashby (Milwaukee Brewers) - W 5",
        "Jos\u00e9 Soriano (Los Angeles Angels) - W 5",
        "George Kirby (Seattle Mariners) - W 4",
        "Landen Roupp (San Francisco Giants) - W 4",
        "Chris Sale (Atlanta Braves) - W 4",
        "Paul Skenes (Pittsburgh Pirates) - W 4",
        "Michael Soroka (Arizona Diamondbacks) - W 4",
        "Gavin Williams (Cleveland Guardians) - W 4"
      ],
      "run_prevention": [
        "Jos\u00e9 Soriano (Los Angeles Angels) - ERA 0.24",
        "Seth Lugo (Kansas City Royals) - ERA 1.15",
        "Parker Messick (Cleveland Guardians) - ERA 1.76",
        "Cam Schlittler (New York Yankees) - ERA 1.77",
        "Randy V\u00e1squez (San Diego Padres) - ERA 1.88",
        "Tyler Glasnow (Los Angeles Dodgers) - WHIP 0.70",
        "Shota Imanaga (Chicago Cubs) - WHIP 0.72",
        "Paul Skenes (Pittsburgh Pirates) - WHIP 0.72",
        "Cam Schlittler (New York Yankees) - WHIP 0.73",
        "Nolan McLean (New York Mets) - WHIP 0.76"
      ]
    }
  }
}